logging_pipeline/__init__.py
logging_pipeline/bootstrap.py
logging_pipeline/version.py
logging_pipeline/wrapt_logging.py
hatch_autorun_logging_pipeline.pth
logging_pipeline-0.5.0.dist-info/METADATA
logging_pipeline-0.5.0.dist-info/WHEEL
logging_pipeline-0.5.0.dist-info/licenses/LICENSE
logging_pipeline-0.5.0.dist-info/RECORD
