Metadata-Version: 2.4
Name: logging-pipeline
Version: 0.5.0
Summary: Inject logging handler for printing message in the format captured by pipeline
Project-URL: Github, https://github.com/spacetown/logging_pipeline
Project-URL: Issues, https://github.com/spacetown/logging_pipeline/issues
Author-email: Michael Förderer <michael.foerderer@gmx.de>
License-Expression: BSD-3-Clause
License-File: LICENSE
Keywords: ADO,Azure,GitHub,Pipeline
Classifier: Development Status :: 3 - Alpha
Classifier: Environment :: Console
Classifier: Intended Audience :: Developers
Classifier: Intended Audience :: Science/Research
Classifier: License :: OSI Approved :: BSD License
Classifier: Natural Language :: English
Classifier: Programming Language :: Python
Classifier: Programming Language :: Python :: 3
Classifier: Programming Language :: Python :: 3.8
Classifier: Programming Language :: Python :: 3.9
Classifier: Programming Language :: Python :: 3.10
Classifier: Programming Language :: Python :: 3.11
Classifier: Programming Language :: Python :: 3.12
Classifier: Programming Language :: Python :: 3.13
Classifier: Topic :: Software Development
Classifier: Topic :: Software Development :: Quality Assurance
Classifier: Topic :: Software Development :: Testing
Classifier: Topic :: Utilities
Requires-Python: >=3.8
Requires-Dist: wrapt>=1.10.4
